{
  "_class": "symbolInstance",
  "booleanOperation": -1,
  "clippingMaskMode": 0,
  "do_objectID": "B5B32C35-067F-4087-9332-F4CEF815F4A9",
  "exportOptions": {
    "_class": "exportOptions",
    "exportFormats": [
    ],
    "includedLayerIds": [
    ],
    "layerOptions": 0,
    "shouldTrim": false
  },
  "frame": {
    "_class": "rect",
    "constrainProportions": false,
    "height": 259,
    "width": 188,
    "x": 20,
    "y": 503
  },
  "hasClippingMask": false,
  "horizontalSpacing": 0,
  "isFixedToViewport": false,
  "isFlippedHorizontal": false,
  "isFlippedVertical": false,
  "isLocked": false,
  "isVisible": true,
  "layerListExpandedType": 1,
  "name": "CRProductCard",
  "nameIsFixed": false,
  "overrideValues": [
    {
      "_class": "overrideValue",
      "overrideName": "FB3A6D65-4829-4BDD-B605-A0FF50231DB2_stringValue",
      "value": "'Kies"
    },
    {
      "_class": "overrideValue",
      "overrideName": "76209EC7-9C0E-4F48-B70F-6265DB8FE7A4_stringValue",
      "value": "Galleta de Maple con tocino"
    }
  ],
  "resizingConstraint": 63,
  "resizingType": 0,
  "rotation": 0,
  "scale": 1,
  "shouldBreakMaskChain": false,
  "style": {
    "_class": "style",
    "blur": {
      "_class": "blur",
      "center": "{0.5, 0.5}",
      "isEnabled": false,
      "motionAngle": 0,
      "radius": 10,
      "saturation": 1,
      "type": 0
    },
    "borderOptions": {
      "_class": "borderOptions",
      "dashPattern": [
      ],
      "isEnabled": true,
      "lineCapStyle": 0,
      "lineJoinStyle": 0
    },
    "borders": [
    ],
    "colorControls": {
      "_class": "colorControls",
      "brightness": 0,
      "contrast": 1,
      "hue": 0,
      "isEnabled": false,
      "saturation": 1
    },
    "contextSettings": {
      "_class": "graphicsContextSettings",
      "blendMode": 0,
      "opacity": 1
    },
    "do_objectID": "F2D0093B-69FC-4C6B-8440-316659D78426",
    "endMarkerType": 0,
    "fills": [
    ],
    "innerShadows": [
    ],
    "miterLimit": 10,
    "shadows": [
    ],
    "startMarkerType": 0,
    "windingRule": 1
  },
  "symbolID": "226C99E8-15DD-4670-8B78-259D68CA0EF4",
  "userInfo": {
    "com.invisionlabs.data": {
      "json-plugin-data": "{\"name\":\"https:\\/\\/canastarosa.com\\/api\\/v1\\/featured\\/market\\/products\\/\",\"paths\":{\"selection\":[],\"repeat\":[\"product\",\"store\",\"name\"]},\"path\":\"BE568A43-1E4B-4008-88FE-FD24752C67AB.json\"}"
    }
  },
  "verticalSpacing": 0
}