{
  "_class": "group",
  "booleanOperation": -1,
  "clippingMaskMode": 0,
  "do_objectID": "EBD9C2D0-1F55-428F-990A-9140F022425C",
  "exportOptions": {
    "_class": "exportOptions",
    "exportFormats": [
    ],
    "includedLayerIds": [
    ],
    "layerOptions": 0,
    "shouldTrim": false
  },
  "frame": {
    "_class": "rect",
    "constrainProportions": false,
    "height": 114,
    "width": 321,
    "x": 0,
    "y": 0
  },
  "groupLayout": {
    "_class": "MSImmutableFreeformGroupLayout"
  },
  "hasClickThrough": false,
  "hasClippingMask": false,
  "isFixedToViewport": false,
  "isFlippedHorizontal": false,
  "isFlippedVertical": false,
  "isLocked": false,
  "isVisible": true,
  "layerListExpandedType": 0,
  "layers": [
    {
      "class": "rectangle",
      "id": "D0E94D17-AA71-4ED9-B3BD-96D0BF0BA73C"
    },
    {
      "class": "group",
      "id": "03B2DEE0-3E47-4F95-86A5-497EE5EFDAB8"
    },
    {
      "class": "group",
      "id": "6EBAA118-C602-4AE6-B7FF-B52367415BFC"
    },
    {
      "class": "bitmap",
      "id": "FCFC193D-C355-4400-81E4-B140A1A370F8"
    },
    {
      "class": "group",
      "id": "CB63EC38-5DCF-4F30-A1E8-7249D75A5CE7"
    },
    {
      "class": "group",
      "id": "1E17EC6F-986C-465D-A030-B910C1A28B49"
    },
    {
      "class": "shapePath",
      "id": "1A8CAF56-9241-4B60-A2AF-3A572127B441"
    }
  ],
  "name": "menu",
  "nameIsFixed": true,
  "resizingConstraint": 63,
  "resizingType": 0,
  "rotation": 0,
  "shouldBreakMaskChain": false,
  "style": {
    "_class": "style",
    "blur": {
      "_class": "blur",
      "center": "{0.5, 0.5}",
      "isEnabled": false,
      "motionAngle": 0,
      "radius": 10,
      "saturation": 1,
      "type": 0
    },
    "borderOptions": {
      "_class": "borderOptions",
      "dashPattern": [
      ],
      "isEnabled": true,
      "lineCapStyle": 0,
      "lineJoinStyle": 0
    },
    "borders": [
    ],
    "colorControls": {
      "_class": "colorControls",
      "brightness": 0,
      "contrast": 1,
      "hue": 0,
      "isEnabled": false,
      "saturation": 1
    },
    "contextSettings": {
      "_class": "graphicsContextSettings",
      "blendMode": 0,
      "opacity": 1
    },
    "do_objectID": "E07B47B5-85DA-40A9-826F-1EF6E3995AE6",
    "endMarkerType": 0,
    "fills": [
    ],
    "innerShadows": [
    ],
    "miterLimit": 10,
    "shadows": [
    ],
    "startMarkerType": 0,
    "windingRule": 1
  }
}